nmrpeaklists/__init__.py
nmrpeaklists/columns.py
nmrpeaklists/files.py
nmrpeaklists/peaklist.py
nmrpeaklists/utils.py
nmrpeaklists-0.9.0.data/scripts/cara2tab
nmrpeaklists-0.9.0.data/scripts/cluster_tab
nmrpeaklists-0.9.0.data/scripts/comment_peaklist
nmrpeaklists-0.9.0.data/scripts/filter_NOESY_fits
nmrpeaklists-0.9.0.data/scripts/filter_spin_links
nmrpeaklists-0.9.0.data/scripts/find_eliminated_spin_links
nmrpeaklists-0.9.0.data/scripts/print_tab_clusters
nmrpeaklists-0.9.0.dist-info/LICENSE
nmrpeaklists-0.9.0.dist-info/METADATA
nmrpeaklists-0.9.0.dist-info/WHEEL
nmrpeaklists-0.9.0.dist-info/top_level.txt
nmrpeaklists-0.9.0.dist-info/RECORD
