Metadata-Version: 2.1
Name: nmrpeaklists
Version: 0.9.0
Summary: A Python library for handling NMR peak lists
Home-page: 
Author: Bradley J. Harden
Author-email: Bradley Harden <bradleyharden@gmail.com>
License: The MIT License (MIT)
Project-URL: Homepage, https://github.com/bradleyharden/nmrpeaklists
Classifier: Programming Language :: Python :: 3
Classifier: License :: OSI Approved :: MIT License
Classifier: Operating System :: OS Independent
Requires-Python: >=3.6
License-File: LICENSE
